emailer/__init__.py
emailer/setup_emailer.py
emailerpy-2.0.dist-info/METADATA
emailerpy-2.0.dist-info/WHEEL
emailerpy-2.0.dist-info/top_level.txt
emailerpy-2.0.dist-info/RECORD
