Metadata-Version: 2.1
Name: emailerpy
Version: 2.0
Summary: Un module Python pour envoyer des emails facilement
Home-page: https://github.com/Nicaisse/Emailer_Python.git
Author: Nicaisse Bryan et Jean Ritchy-Bastien
Author-email: bryannicaisse2001@gmail.com
